<annotation>
	<folder>annotations</folder>
	<filename>ball44.jpg</filename>
	<path>C:\Users\Melis\OneDrive\Dokumente\BA\annotations\ball44.jpg</path>
	<source>
		<database>Unknown</database>
	</source>
	<size>
		<width>640</width>
		<height>360</height>
		<depth>3</depth>
	</size>
	<segmented>0</segmented>
	<object>
		<name>ball</name>
		<pose>Unspecified</pose>
		<truncated>0</truncated>
		<difficult>0</difficult>
		<bndbox>
			<xmin>191</xmin>
			<ymin>51</ymin>
			<xmax>245</xmax>
			<ymax>99</ymax>
		</bndbox>
	</object>
	<object>
		<name>ball</name>
		<pose>Unspecified</pose>
		<truncated>0</truncated>
		<difficult>0</difficult>
		<bndbox>
			<xmin>236</xmin>
			<ymin>33</ymin>
			<xmax>293</xmax>
			<ymax>85</ymax>
		</bndbox>
	</object>
	<object>
		<name>ball</name>
		<pose>Unspecified</pose>
		<truncated>0</truncated>
		<difficult>0</difficult>
		<bndbox>
			<xmin>390</xmin>
			<ymin>229</ymin>
			<xmax>441</xmax>
			<ymax>277</ymax>
		</bndbox>
	</object>
</annotation>
